torch_repr_shape/__init__.py
torch_repr_shape/patch.py
torch_repr_shape-0.0.2.dist-info/METADATA
torch_repr_shape-0.0.2.dist-info/WHEEL
torch_repr_shape-0.0.2.dist-info/top_level.txt
torch_repr_shape-0.0.2.dist-info/RECORD
