Metadata-Version: 2.4
Name: torch_repr_shape
Version: 0.0.2
Summary: Patch torch.Tensor.__repr__ to include tensor shape.
Requires-Python: >=3.8
